{
  "mysticmod:BentSpoon": {
    "NAME": "弯勺",
    "FLAVOR": "李所不想让你知道的是，其实这里根本没有勺子。",
    "DESCRIPTIONS": ["#y戏法牌 额外造成1点伤害，额外提供1点 #y格挡 。"]
  },
  "mysticmod:BlessedBook": {
    "NAME": "祝福书",
    "FLAVOR": "经过神秘魔法加持的强力法术书。",
    "DESCRIPTIONS": ["替换 #y法术书 。每 ", " 个回合开始时，将一张随机 #y戏法牌 加入你的手牌。"]
  },
  "mysticmod:CrystalBall": {
    "NAME": "水晶球",
    "FLAVOR": "看来并不能和真知晶球，冥想盆，探知球，偏光晶体，格雷莫海因球，或是乌陵与土明联通。",
    "DESCRIPTIONS": ["所有非 [#FF5252]战技牌[] 的技能牌视作 [#5299E0]法术牌[] ，所有非 [#5299E0]法术牌[] 的攻击牌视作 [#FF5252]战技牌[] 。"]
  },
  "mysticmod:DeckOfManyThings": {
    "NAME": "万象无常牌",
    "FLAVOR": "搞不明白为什么会有人用一副卡牌来描述魔法效果。",
    "DESCRIPTIONS": ["在每个回合开始时，获得 [E] 。在每个回合结束时，如果本回合你没有打出至少两张 [#5299E0]法术牌[] 和两张 [#FF5252]战技牌[] ，失去2点生命。"]
  },
  "mysticmod:Kama": {
    "NAME": "单镰",
    "FLAVOR": "通常用来收割麦子，以及灵魂。",
    "DESCRIPTIONS": ["每打出 5 张牌，其中最后一张如果是 [#FF5252]战技牌[] ，获得1点 #y力量 ；如果是 [#5299E0]法术牌[] ，获得1点 #y敏捷 。"]
  },
  "mysticmod:RunicPrism": {
    "NAME": "符文棱镜",
    "FLAVOR": "月之神明的暗面。",
    "DESCRIPTIONS": ["每当你打出一张 [#5299E0]法术牌[] ，对一个随机敌人造成 #b3 点伤害。"]
  },
  "mysticmod:RabbitsFoot": {
    "NAME": "幸运兔足",
    "FLAVOR": "据说能给持有者带来好运。",
    "DESCRIPTIONS": ["每当你打出一张 [#FF5252]战技牌[] ，获得1点 #y格挡 。"]
  },
  "mysticmod:SpellBook": {
    "NAME": "法术书",
    "FLAVOR": "为每个施法者所特有，上面记载的法术只有作者本人才看得懂。",
    "DESCRIPTIONS": ["每场战斗开始时，将一张随机 #y戏法牌 加入你的手牌。"]
  },
  "mysticmod:TrainingManual": {
    "NAME": "训练手册",
    "FLAVOR": "一本包含各种战斗风格插画的小册子，上面的字迹意外地熟悉。",
    "DESCRIPTIONS": ["在每场战斗开始时，将一张随机 [#FF5252]战技牌[] 加入你的手牌。"]
  }
}